setup.cfg
setup.py
aiospread/__init__.py
aiospread/client.py
aiospread/exceptions.py
aiospread/models.py
aiospread/urls.py
aiospread/utils.py
aiospread.egg-info/PKG-INFO
aiospread.egg-info/SOURCES.txt
aiospread.egg-info/dependency_links.txt
aiospread.egg-info/requires.txt
aiospread.egg-info/top_level.txt