Metadata-Version: 1.1
Name: aiospread
Version: 1.0.0
Summary: Google Spreadsheets Python API
Home-page: https://github.com/RainbowLegend/aiospread
Author: Anton Burnashev
Author-email: fuss.here@gmail.com
License: MIT
Keywords: spreadsheets,google-spreadsheets,asyncio
Platform: UNKNOWN
Classifier: Programming Language :: Python
Classifier: Programming Language :: Python :: 3.6
Classifier: License :: OSI Approved :: MIT License
Classifier: Operating System :: OS Independent
Classifier: Development Status :: 3 - Alpha
Classifier: Intended Audience :: Developers
Classifier: Intended Audience :: End Users/Desktop
Classifier: Intended Audience :: Science/Research
Classifier: Topic :: Office/Business :: Financial :: Spreadsheet
Classifier: Topic :: Software Development :: Libraries :: Python Modules
